avesterra/__init__.py
avesterra/annotation.py
avesterra/api.py
avesterra/aspects.py
avesterra/attributions.py
avesterra/av_log.py
avesterra/av_logging.py
avesterra/avesterra.py
avesterra/avial.py
avesterra/avial_model.py
avesterra/collections.py
avesterra/columns.py
avesterra/compartments.py
avesterra/credential.py
avesterra/facets.py
avesterra/factors.py
avesterra/facts.py
avesterra/features.py
avesterra/fields.py
avesterra/files.py
avesterra/firewall.py
avesterra/folders.py
avesterra/frames.py
avesterra/generals.py
avesterra/hgtp.py
avesterra/identities.py
avesterra/items.py
avesterra/objects.py
avesterra/outlets.py
avesterra/parameters.py
avesterra/predefined.py
avesterra/properties.py
avesterra/registries.py
avesterra/routing.py
avesterra/rows.py
avesterra/spaces.py
avesterra/tables.py
avesterra/taxonomy.py
avesterra/tokens.py
avesterra/traits.py
avesterra/trash.py
avesterra/tunnels.py
avesterra/certificates/__init__.py
avesterra/certificates/avesterra.pem
machinations/__init__.py
machinations/adapter.py
machinations/control_surface.py
machinations/event_handler.py
machinations/routable_adapter.py
machinations/routable_event_handler.py
orchestra/__init__.py
orchestra/env.py
orchestra/interface.py
orchestra/utils.py
midwksl_ksi-25.7.6.dist-info/METADATA
midwksl_ksi-25.7.6.dist-info/WHEEL
midwksl_ksi-25.7.6.dist-info/top_level.txt
midwksl_ksi-25.7.6.dist-info/RECORD
