Metadata-Version: 2.4
Name: midwksl_ksi
Version: 25.7.6
Summary: Python Knowledge Space Interaction Library
Author: Midwest Knowledge System Labs
Author-email: apl@midwksl.net ; avesterra@georgetown.edu ; dev@ledr.io
License: GPL 3.0
Classifier: Programming Language :: Python :: 3.13
Classifier: Intended Audience :: Developers
Classifier: Topic :: Internet
Requires-Python: >=3.12
Requires-Dist: tabulate
Dynamic: author
Dynamic: author-email
Dynamic: classifier
Dynamic: license
Dynamic: requires-dist
Dynamic: requires-python
Dynamic: summary
